[
  {
    "title": "AWS Certified Solutions Architect - Associate",
    "imageUrl": "assets/images/SAA.png",
    "verifyUrl": "https://www.credly.com/badges/47aab480-9f01-4be1-b5f5-2cff9adab13b/public_url"
  },
  {
    "title": "AWS Certified Data Engineer – Associate",
    "imageUrl": "assets/images/DEA.png",
    "verifyUrl": "https://www.credly.com/badges/3884c795-e125-4199-8897-f498fd3109ca/public_url"
  },
  {
    "title": "AWS Certified Cloud Practitioner",
    "imageUrl": "assets/images/CCP.png",
    "verifyUrl": "https://www.credly.com/badges/9c9b09dd-b597-494e-a4c3-148baa286aba/public_url"
  },
  {
    "title": "AWS Certified AI Practitioner",
    "imageUrl": "assets/images/AIF.png",
    "verifyUrl": "https://www.credly.com/badges/95d59989-d9d0-4117-aae2-0756f54e4765/public_url"
  },
  {
    "title": "HashiCorp Certified: Terraform Associate (003)",
    "imageUrl": "assets/images/terraform.png",
    "verifyUrl": "https://www.credly.com/badges/95d59989-d9d0-4117-aae2-0756f54e4765/public_url"
  }
] 